{"cameraMode":{"drawMode":0,"name":"Shaded","section":"Shading Mode"},"sceneLighting":true,"audioPlay":false,"sceneViewState":{"m_AlwaysRefresh":false,"showFog":true,"showSkybox":true,"showFlares":true,"showImageEffects":true,"showParticleSystems":true,"showVisualEffectGraphs":true,"m_FxEnabled":true},"in2DMode":false,"pivot":{"x":-224.30953979492188,"y":-258.1586608886719,"z":349.6570739746094},"rotation":{"x":0.2586800754070282,"y":-0.2621881663799286,"z":0.0733039453625679,"w":0.9268187880516052},"size":255.42330932617188,"orthographic":false}